RsAreg800/RsAreg800.py
RsAreg800/__init__.py
RsAreg800/enums.py
RsAreg800/repcap.py
RsAreg800/CustomFiles/__init__.py
RsAreg800/CustomFiles/events.py
RsAreg800/CustomFiles/utilities.py
RsAreg800/Implementations/FormatPy.py
RsAreg800/Implementations/Kboard.py
RsAreg800/Implementations/Memory.py
RsAreg800/Implementations/Unit.py
RsAreg800/Implementations/__init__.py
RsAreg800/Implementations/Calibration/Frequency.py
RsAreg800/Implementations/Calibration/Tselected.py
RsAreg800/Implementations/Calibration/__init__.py
RsAreg800/Implementations/Calibration/All/Measure.py
RsAreg800/Implementations/Calibration/All/__init__.py
RsAreg800/Implementations/Calibration/Data/Factory.py
RsAreg800/Implementations/Calibration/Data/__init__.py
RsAreg800/Implementations/Calibration/Data/Update/__init__.py
RsAreg800/Implementations/Calibration/Data/Update/Level/Force.py
RsAreg800/Implementations/Calibration/Data/Update/Level/__init__.py
RsAreg800/Implementations/Calibration/Delay/Shutdown.py
RsAreg800/Implementations/Calibration/Delay/__init__.py
RsAreg800/Implementations/Calibration/Level/Attenuator.py
RsAreg800/Implementations/Calibration/Level/__init__.py
RsAreg800/Implementations/Calibration/Roscillator/Data.py
RsAreg800/Implementations/Calibration/Roscillator/Store.py
RsAreg800/Implementations/Calibration/Roscillator/__init__.py
RsAreg800/Implementations/Calibration/Selected/Measure.py
RsAreg800/Implementations/Calibration/Selected/__init__.py
RsAreg800/Implementations/Device/__init__.py
RsAreg800/Implementations/Device/Settings/Backup.py
RsAreg800/Implementations/Device/Settings/Restore.py
RsAreg800/Implementations/Device/Settings/__init__.py
RsAreg800/Implementations/Diagnostic/BgInfo.py
RsAreg800/Implementations/Diagnostic/Service.py
RsAreg800/Implementations/Diagnostic/__init__.py
RsAreg800/Implementations/Diagnostic/Debug/Page.py
RsAreg800/Implementations/Diagnostic/Debug/__init__.py
RsAreg800/Implementations/Diagnostic/Eeprom/Customize.py
RsAreg800-5.30.49.dist-info/METADATA
RsAreg800-5.30.49.dist-info/WHEEL
RsAreg800-5.30.49.dist-info/top_level.txt
RsAreg800-5.30.49.dist-info/RECORD
